[
  {
    "id": "87",
    "place_of_revelation": "makkah",
    "transliterated_name": "Al-A'la",
    "translated_name": "The Most High",
    "verse_count": 19,
    "slug": "al-ala",
    "codepoints": [
      1575,
      1604,
      1571,
      1593,
      1604,
      1609
    ],
    "translated_by": "Hussein Taji Kal Dari"
  },
  [
    1,
    "نام پروردگار بلند مرتبه‌ات را به پاکی یاد کن."
  ],
  [
    2,
    "(همان) که آفرید پس درست و استوار ساخت."
  ],
  [
    3,
    "و (همان) کسی‌که اندازه گیری کرد پس هدایت نمود."
  ],
  [
    4,
    "و (آن) کسی‌که چراگاه را رویانید."
  ],
  [
    5,
    "سپس آن را خشک و سیاه گردانید."
  ],
  [
    6,
    "ما بزودی (قرآن را) بر تو می‌خوانیم، پس هرگز فراموش نخواهی کرد."
  ],
  [
    7,
    "مگر آنچه را که الله بخواهد، همانا او آشکار و نهان را می‌داند."
  ],
  [
    8,
    "و ما تو را برای (راه) آسان توفیق می‌دهیم."
  ],
  [
    9,
    "پس اگر پند مفید باشد، پند ده."
  ],
  [
    10,
    "بزودی کسی‌که (از الله) می‌ترسد، پند می‌پذیرد."
  ],
  [
    11,
    "و بدبخت‌ترین (مردم) از آن دوری می‌گزیند."
  ],
  [
    12,
    "(همان) کسی‌که در آتش بزرگ (جهنم) در خواهد آمد."
  ],
  [
    13,
    "سپس در آن (آتش) نه می‌میرد و نه زنده می‌ماند."
  ],
  [
    14,
    "یقیناً کسی‌که خود را پاک (و تزکیه) کند، رستگار شد."
  ],
  [
    15,
    "و (نیز کسی که) نام پروردگارش را یادکرد پس نماز گزارد."
  ],
  [
    16,
    "بلکه شما (مردم) زندگی دنیا را (بر آخرت) ترجیح می‌دهید."
  ],
  [
    17,
    "در حالی‌که آخرت بهتر و پاینده‌تر است."
  ],
  [
    18,
    "به راستی این (فحوا) در صحیفه‌های پیشین (نیز) بود."
  ],
  [
    19,
    "صحیفه‌های ابراهیم و موسی."
  ]
]