[
  {
    "id": "108",
    "place_of_revelation": "makkah",
    "transliterated_name": "Al-Kawthar",
    "translated_name": "The Abundance",
    "verse_count": 3,
    "slug": "al-kawthar",
    "codepoints": [
      1575,
      1604,
      1603,
      1608,
      1579,
      1585
    ]
  },
  [
    1,
    "Indeed, We have granted you ˹O Prophet˺ abundant goodness."
  ],
  [
    2,
    "So pray and sacrifice to your Lord ˹alone˺."
  ],
  [
    3,
    "Only the one who hates you is truly cut off ˹from any goodness˺."
  ]
]